smartcliapp/__init__.py
smartcliapp/climanager.py
smartcliapp/informer.py
smartcliapp-0.4.2.dist-info/licenses/LICENSE
smartcliapp-0.4.2.dist-info/METADATA
smartcliapp-0.4.2.dist-info/WHEEL
smartcliapp-0.4.2.dist-info/top_level.txt
smartcliapp-0.4.2.dist-info/RECORD
