Metadata-Version: 2.4
Name: smartcliapp
Version: 0.4.2
Summary: Cross-platform library of tools for creating console applications, based on the click library.
Home-page: https://github.com/smartlegionlab/smartcliapp
Author: A.A. Suvorov
Author-email: smartlegiondev@gmail.com
License: BSD 3-Clause License
Project-URL: Documentation, https://github.com/smartlegionlab/smartcliapp/blob/master/README.md
Project-URL: Release notes, https://github.com/smartlegionlab/smartcliapp/releases
Keywords: smartlegionlab,click,smart cli app,console application,create cli
Classifier: Development Status :: 5 - Production/Stable
Classifier: Environment :: Console
Classifier: Intended Audience :: End Users/Desktop
Classifier: Intended Audience :: System Administrators
Classifier: License :: OSI Approved :: BSD License
Classifier: Natural Language :: English
Classifier: Operating System :: OS Independent
Classifier: Operating System :: Microsoft :: Windows
Classifier: Operating System :: POSIX :: Linux
Classifier: Programming Language :: Python :: 3 :: Only
Classifier: Topic :: Software Development :: Libraries :: Python Modules
Classifier: Topic :: Utilities
Requires-Python: >=3.6
License-File: LICENSE
Requires-Dist: smartprinter~=0.2.1
Requires-Dist: click~=8.0.1
Dynamic: license-file
